AdvancedEncryptionStandard/__init__.py
AdvancedEncryptionStandard/Cipher/AESoperations.py
AdvancedEncryptionStandard/Cipher/AESstatic.py
AdvancedEncryptionStandard/Cipher/Crypto.py
AdvancedEncryptionStandard/Cipher/__init__.py
AdvancedEncryptionStandard/IO/Converter.py
AdvancedEncryptionStandard/IO/Error.py
AdvancedEncryptionStandard/IO/__init__.py
AdvancedEncryptionStandard/Math/Matrix.py
AdvancedEncryptionStandard/Math/__init__.py
AdvancedEncryptionStandard-1.0.0.dist-info/LICENSE.txt
AdvancedEncryptionStandard-1.0.0.dist-info/METADATA
AdvancedEncryptionStandard-1.0.0.dist-info/WHEEL
AdvancedEncryptionStandard-1.0.0.dist-info/top_level.txt
AdvancedEncryptionStandard-1.0.0.dist-info/RECORD
