Metadata-Version: 2.1
Name: AdvancedEncryptionStandard
Version: 1.0.0
Summary: Advanced Encryption Standard
Author-email: ShiXun <tomcruise890604@gmail.com>
Project-URL: Homepage, https://github.com/ShiXun0604/AdvancedEncryptionStandard
Project-URL: Issues, https://github.com/ShiXun0604/AdvancedEncryptionStandard/issues
Classifier: Programming Language :: Python :: 3
Classifier: License :: OSI Approved :: MIT License
Classifier: Operating System :: OS Independent
Requires-Python: >=3.9
License-File: LICENSE.txt
